{
  "title": "刀劍神域劇場版 -Progressive- 陰沉薄暮的詼諧曲 (Sword Art Online the Movie -Progressive- Scherzo of Deep Night, 2022)",
  "imdb": "https://www.imdb.com/title/tt15830702/",
  "description": "本部劇場版是描述在TV版系列中所沒出現過的浮游城《艾恩葛朗特》第5層的故事。在已公開的預告片中，出現了放著攻略遊戲不管只沉溺於PK（獵殺玩家）的集團、對著亞絲娜拔刀相向的不明人士、以及披著黑色風衣的男人緊逼而來！另外，似乎透漏兩大公會正發生著什麼問題的「想要通關這個遊戲，DKB跟ALS都是必需的」的這句話又有著什麼含意？桐人和亞絲娜在前作就參戰的米特、亞魯戈以及艾基爾的協力之下挺身對抗Boss，然而出現在桐人面前的卻是與封測時不同的強大怪物──。究竟桐人與亞絲娜等人能否成功通關第五層呢！？",
  "cover": "sao_progress_kuraki_yuuyami_no_scherzo.jpg",
  "time": "1 小時 41 分鐘",
  "release": "06/02 (五) 21:30",
  "trailer": "https://youtu.be/GPBrslQRF1g",
  "watched": true
}
